needle/__init__.py
needle/autograd.py
needle/backend_numpy.py
needle/backend_selection.py
needle/data.py
needle/init.py
needle/nn.py
needle/ops.py
needle/optim.py
needle/backend_ndarray/__init__.py
needle/backend_ndarray/ndarray.py
needle/backend_ndarray/ndarray_backend_cpu.cpython-310-x86_64-linux-gnu.so
needle/backend_ndarray/ndarray_backend_cuda.cpython-310-x86_64-linux-gnu.so
needle/backend_ndarray/ndarray_backend_numpy.py
needleTensor-0.0.3.dist-info/LICENSE
needleTensor-0.0.3.dist-info/METADATA
needleTensor-0.0.3.dist-info/WHEEL
needleTensor-0.0.3.dist-info/top_level.txt
needleTensor-0.0.3.dist-info/RECORD
