Metadata-Version: 2.1
Name: needleTensor
Version: 0.0.3
Summary: A mini pytorch, which contains necessary element if deep learning framwork.
Home-page: https://github.com/Xiangjun-Qu/NeedleTensor
Author: Xiangjun Qu
Author-email: quxiangjun@mail.ustc.edu.cn
Classifier: Development Status :: 3 - Alpha
Classifier: Intended Audience :: Developers
Classifier: License :: OSI Approved :: MIT License
Classifier: Programming Language :: Python :: 3
Classifier: Programming Language :: Python :: 3.8
Classifier: Programming Language :: Python :: 3.9
Classifier: Programming Language :: Python :: 3.10
Classifier: Programming Language :: Python :: 3.11
Classifier: Topic :: Software Development :: Libraries
Classifier: Topic :: Utilities
License-File: LICENSE
Requires-Dist: numpy
